wilhelmina/__init__.py
wilhelmina/client.py
wilhelmina/models/__init__.py
wilhelmina/models/messages.py
wilhelmina/py.typed
wilhelmina/tests/__init__.py
wilhelmina/tests/conftest.py
wilhelmina/tests/test_client.py
wilhelmina/tests/test_error_handling.py
wilhelmina/tests/test_init.py
wilhelmina/tests/test_models.py
wilhelmina/tests/test_unread_messages.py
wilhelmina/tests/test_utils.py
wilhelmina/utils/__init__.py
wilhelmina-0.1.9.dist-info/LICENSE
wilhelmina-0.1.9.dist-info/METADATA
wilhelmina-0.1.9.dist-info/WHEEL
wilhelmina-0.1.9.dist-info/entry_points.txt
wilhelmina-0.1.9.dist-info/RECORD
