Metadata-Version: 2.3
Name: wilhelmina
Version: 0.1.9
Summary: API client for Wilma school portal
License: MIT
Author: Frank Wickström
Author-email: frwickst@gmail.com
Requires-Python: >=3.13,<4.0
Classifier: License :: OSI Approved :: MIT License
Classifier: Programming Language :: Python :: 3
Classifier: Programming Language :: Python :: 3.13
Provides-Extra: aiohttp
Provides-Extra: playwright
Requires-Dist: aiohttp[speedups] (>=3.11.16,<4.0.0) ; extra == "aiohttp"
Requires-Dist: beautifulsoup4 (>=4.13.4,<5.0.0)
Requires-Dist: html2text (>=2025.4.15,<2026.0.0)
Requires-Dist: mashumaro (>=3.15,<4.0)
Requires-Dist: playwright (>=1.51.0,<2.0.0) ; extra == "playwright"
Project-URL: Repository, https://github.com/frwickst/wilma
